htlll_runner/__init__.py
htlll_runner/__main__.py
htlll_runner-0.0.1.dist-info/METADATA
htlll_runner-0.0.1.dist-info/WHEEL
htlll_runner-0.0.1.dist-info/entry_points.txt
htlll_runner-0.0.1.dist-info/top_level.txt
htlll_runner-0.0.1.dist-info/RECORD
