Metadata-Version: 2.1
Name: htlll-runner
Version: 0.0.1
Summary: A simple python package to run htlll
Home-page: https://github.com/Moosems/htlll_runner
Author: Moosems
Author-email: moosems.j@gmail.com
Requires-Dist: ply
